{
  "id": "pot-iron",
  "name": "Iron Pot",
  "description": "A sturdy iron cooking pot with a lid. Can hold 1 gallon of liquid and is suitable for cooking meals over a fire. Essential for preparing hot meals during travel.",
  "price": 200,
  "type": "Adventuring Gear",
  "weight": 10,
  "stack": 1,
  "ac": null,
  "damage": null,
  "heal": null,
  "img": "equipment/adventuring-gear.jpg",
  "rarity": "common",
  "tags": [],
  "ai_description": "Black iron cooking pot with heavy lid and sturdy handle",
  "notes": [],
  "range": "null",
  "range-long": "null",
  "ammunition": "",
  "image": "/res/img/items/pot-iron.png"
}