{
  "id": "scholars-pack",
  "name": "Scholar's Pack",
  "description": "An academic's kit containing scholarly supplies and research materials for traveling scholars and wizards. Unpacking equips a backpack and places all contents inside it.",
  "price": 3902,
  "type": "Pack",
  "weight": 40,
  "stack": 1,
  "gear_slot": "consumable",
  "rarity": "common",
  "tags": [
    "pack"
  ],
  "contents": [
    [
      "backpack",
      1
    ],
    [
      "robes",
      1
    ],
    [
      "book",
      1
    ],
    [
      "ink",
      1
    ],
    [
      "ink-pen",
      1
    ],
    [
      "lamp",
      1
    ],
    [
      "parchment",
      10
    ],
    [
      "tinderbox",
      1
    ],
    [
      "dagger",
      1
    ],
    [
      "rope",
      1
    ]
  ]
}